hchiam/__init__.py
hchiam-1.0.0.dist-info/LICENSE
hchiam-1.0.0.dist-info/METADATA
hchiam-1.0.0.dist-info/WHEEL
hchiam-1.0.0.dist-info/entry_points.txt
hchiam-1.0.0.dist-info/top_level.txt
hchiam-1.0.0.dist-info/RECORD
