Metadata-Version: 2.1
Name: hchiam
Version: 1.0.0
License: MIT License
Project-URL: Source, https://github.com/pypa/hchiam/
Classifier: License :: OSI Approved :: MIT License
Classifier: Programming Language :: Python :: 3
Requires-Python: >=3.7
License-File: LICENSE
